mercurydsa/__init__.py
mercurydsa/src/__init__.py
mercurydsa/src/cli.py
mercurydsa/src/core/__init__.py
mercurydsa/src/core/exceptions.py
mercurydsa/src/core/layout_linear.py
mercurydsa/src/core/layout_tree.py
mercurydsa/src/type/__init__.py
mercurydsa/src/type/deque.py
mercurydsa/src/type/linked_list.py
mercurydsa/src/type/stack.py
mercurydsa-0.0.16.dist-info/METADATA
mercurydsa-0.0.16.dist-info/WHEEL
mercurydsa-0.0.16.dist-info/entry_points.txt
mercurydsa-0.0.16.dist-info/top_level.txt
mercurydsa-0.0.16.dist-info/RECORD
