Metadata-Version: 2.1
Name: mercurydsa
Version: 0.0.16
Summary: python package to implement data structures
Author: Walter Michel Raja
Author-email: waltermichelraja@gmail.com
License: MIT
Classifier: License :: OSI Approved :: MIT License
Classifier: Programming Language :: Python :: 3
Classifier: Programming Language :: Python :: 3.9
